LICENSE
MANIFEST.in
PKG-INFO.in
README.rst
setup.cfg
setup.py
lib/django_hotsauce_oauthclient.egg-info/PKG-INFO
lib/django_hotsauce_oauthclient.egg-info/SOURCES.txt
lib/django_hotsauce_oauthclient.egg-info/dependency_links.txt
lib/django_hotsauce_oauthclient.egg-info/top_level.txt
lib/wsgi_oauth2/__init__.py
lib/wsgi_oauth2/client.py
lib/wsgi_oauth2/controller.py
lib/wsgi_oauth2/provider.py
lib/wsgi_oauth2/util.py