Metadata-Version: 1.2
Name: django-hotsauce-oauthclient
Version: 0.3
Summary: Simple WSGI middleware for OAuth 2.0
Home-page: UNKNOWN
Author-email: tkadm30@yandex.com
Maintainer: Etienne Robillard
License: Apache
Platform: UNKNOWN
Classifier: Environment :: Web Environment
Classifier: Intended Audience :: Developers
Classifier: Intended Audience :: System Administrators
Classifier: Programming Language :: Python :: 2.7
Classifier: Programming Language :: Python :: 3
Classifier: Programming Language :: Python :: 3.2
Classifier: Programming Language :: Python :: 3.3
Classifier: Programming Language :: Python :: 3.4
Classifier: Topic :: Internet :: WWW/HTTP :: WSGI :: Middleware
